COPYING.txt
MANIFEST.in
README.rst
requirements.txt
requirements_dev.txt
setup.cfg
setup.py
afro/__init__.py
afro/application.py
afro/config.default.yml
afro/config.py
afro/disc_info.py
afro/formater.py
afro/hasher.py
afro/playlist.py
afro/tracks.py
afro/utils.py
afro.egg-info/PKG-INFO
afro.egg-info/SOURCES.txt
afro.egg-info/dependency_links.txt
afro.egg-info/entry_points.txt
afro.egg-info/requires.txt
afro.egg-info/top_level.txt
afro/profiles/default.yml
afro/profiles/flac.yml
afro/profiles/mp3.yml
afro/profiles/ogg.yml