Metadata-Version: 1.1
Name: afro
Version: 0.6.0
Summary: Another Free Ripping Orchestra
Home-page: https://github.com/mathgl67/Afro
Author: mathgl67
Author-email: mathgl67_AT_gmail.com
License:                     GNU GENERAL PUBLIC LICENSE
